ziphyr/__init__.py
ziphyr/retro.py
ziphyr/stream.py
ziphyr/utils.py
ziphyr/ziphyr.py
ziphyr-0.2.0.dist-info/AUTHORS.md
ziphyr-0.2.0.dist-info/LICENSE
ziphyr-0.2.0.dist-info/METADATA
ziphyr-0.2.0.dist-info/WHEEL
ziphyr-0.2.0.dist-info/top_level.txt
ziphyr-0.2.0.dist-info/RECORD
