Metadata-Version: 2.1
Name: ziphyr
Version: 0.2.0
Summary: On-the-fly zip of streamed file with optional zipcrypto.
Home-page: https://github.com/quarkslab/ziphyr
Author: irma-dev
Author-email: irma-dev@quarkslab.com
License: Apache Software License 2.0
Keywords: zip stream crypto ziphyr
Platform: UNKNOWN
Classifier: Development Status :: 3 - Alpha
Classifier: Environment :: Web Environment
Classifier: Intended Audience :: Developers
Classifier: License :: OSI Approved :: Apache Software License
Classifier: Natural Language :: English
Classifier: Programming Language :: Python :: 3
Classifier: Programming Language :: Python :: 3.5
Classifier: Programming Language :: Python :: 3.6
Classifier: Programming Language :: Python :: 3.7
Classifier: Programming Language :: Python :: 3.8
Requires-Python: >=3.5
